JY/__init__.py
JY/exercise45class.py
JY/exercise45runner.py
Jason_s_Demo-2019.11.12.dist-info/METADATA
Jason_s_Demo-2019.11.12.dist-info/WHEEL
Jason_s_Demo-2019.11.12.dist-info/top_level.txt
Jason_s_Demo-2019.11.12.dist-info/RECORD
